COPYING
LICENSE
MANIFEST.in
README.txt
setup.cfg
setup.py
repoman/__init__.py
repoman/__version__.py
repoman/websetup.py
repoman.egg-info/PKG-INFO
repoman.egg-info/SOURCES.txt
repoman.egg-info/dependency_links.txt
repoman.egg-info/entry_points.txt
repoman.egg-info/not-zip-safe
repoman.egg-info/paster_plugins.txt
repoman.egg-info/requires.txt
repoman.egg-info/top_level.txt
repoman/commands/__init__.py
repoman/commands/wsgi_config.py
repoman/config/__init__.py
repoman/config/deployment.ini_tmpl
repoman/config/environment.py
repoman/config/middleware.py
repoman/config/routing.py
repoman/controllers/__init__.py
repoman/controllers/error.py
repoman/controllers/api/__init__.py
repoman/controllers/api/groups.py
repoman/controllers/api/images.py
repoman/controllers/api/raw.py
repoman/controllers/api/users.py
repoman/controllers/api/whoami.py
repoman/lib/__init__.py
repoman/lib/app_globals.py
repoman/lib/authorization.py
repoman/lib/base.py
repoman/lib/beautify.py
repoman/lib/default_db.py
repoman/lib/helpers.py
repoman/lib/middleware/__init__.py
repoman/lib/middleware/authentication.py
repoman/lib/middleware/cascade.py
repoman/lib/middleware/content_length.py
repoman/lib/middleware/filestorage.py
repoman/lib/storage/__init__.py
repoman/lib/storage/storage.py
repoman/model/__init__.py
repoman/model/associations.py
repoman/model/certificate.py
repoman/model/checksum.py
repoman/model/form.py
repoman/model/group.py
repoman/model/image.py
repoman/model/meta.py
repoman/model/permission.py
repoman/model/quota.py
repoman/model/storage.py
repoman/model/user.py
repoman/public/bg.png
repoman/public/favicon.ico
repoman/public/index.html
repoman/public/pylons-logo.gif
repoman/tests/__init__.py
repoman/tests/test_models.py
repoman/tests/functional/__init__.py