Metadata-Version: 1.0
Name: repoman
Version: 0.2.5
Summary: RESTful virtual machine image manager
Home-page: https://github.com/hep-gc/repoman
Author: Matthew Vliet
Author-email: mvliet@uvic.ca
License: GPLv3 or Apache v2
Platform: UNKNOWN
